[
  {
    "id": "page_134_line000",
    "text": "133 § 10. Внешняя политика в 1953—1964 гг.",
    "bbox": [
      0,
      0,
      500,
      15
    ]
  },
  {
    "id": "page_134_line001",
    "text": "Внешнеполитический курс советского руководства в 1953—1964 гг. был ",
    "bbox": [
      0,
      20,
      500,
      35
    ]
  },
  {
    "id": "page_134_line002",
    "text": "основан на принципах мирного сосуществования с капиталистическими странами.Используя исторические знания, приведите два аргумента, которыми можно подтвердить данную точку зрения, и два аргумента, которыми можно опро -",
    "bbox": [
      0,
      40,
      500,
      55
    ]
  },
  {
    "id": "page_134_line003",
    "text": "вергнуть её.",
    "bbox": [
      0,
      60,
      500,
      75
    ]
  },
  {
    "id": "page_134_line004",
    "text": "Работаем с ХРОНОЛОГИЕЙ ",
    "bbox": [
      0,
      80,
      500,
      95
    ]
  },
  {
    "id": "page_134_line005",
    "text": "Расположите в  хронологической последовательности исторические собы-тия. Запишите в тетради цифры, которыми обозначены исторические собы-тия, в правильной последовательности.1) Карибский кризис2) приход к власти на Кубе Ф. Кастро3) политический кризис в Венгрии4) создание Организации Варшавского договора5) Г од Африки",
    "bbox": [
      0,
      100,
      500,
      115
    ]
  },
  {
    "id": "page_134_line006",
    "text": "Работаем с ИСТОЧНИКОМ ",
    "bbox": [
      0,
      120,
      500,
      135
    ]
  },
  {
    "id": "page_134_line007",
    "text": "Прочитайте отрывок из воспоминаний Н. Хрущёва. Выполните задания и от-ветьте на вопросы.",
    "bbox": [
      0,
      140,
      500,
      155
    ]
  },
  {
    "id": "page_134_line008",
    "text": "«Чтобы как-то смягчить обстановку, я предложил членам советского ",
    "bbox": [
      0,
      160,
      500,
      175
    ]
  },
  {
    "id": "page_134_line009",
    "text": "руководства: „Сходим, товарищи, в Большой театр. Сейчас в мире напря-жённая обстановка, а  мы появимся в  театре. Наш народ и  иностранцы будут это видеть, и  это станет действовать успокаивающе. Если Хрущёв и другие лидеры сидят в театре в такое время, то можно спокойно спать“. Но сами-то мы очень тогда беспокоились. Не требуется большого ума, чтобы начать войну. Мы не хотели войны, не хотели сами иметь жертвы и не хотели наносить потери Америке. А если начнётся война? Тогда, как говорится, попал в  драку, не жалей волос. Поэтому я тогда одну самую тревожную ночь провёл даже в Кремле».",
    "bbox": [
      0,
      180,
      500,
      195
    ]
  },
  {
    "id": "page_134_line010",
    "text": " ⬤1. Назовите историческое событие, о котором идёт речь в отрывке. 2. В ка-",
    "bbox": [
      0,
      200,
      500,
      215
    ]
  },
  {
    "id": "page_134_line011",
    "text": "ком году оно произошло? 3. Назовите имя президента США, который при-",
    "bbox": [
      0,
      220,
      500,
      235
    ]
  },
  {
    "id": "page_134_line012",
    "text": "нимал участие в данном историческом событии. 4. Подтвердите цитатами из текста, что руководство СССР не желало перерастания данного историче-ского события в войну.",
    "bbox": [
      0,
      240,
      500,
      255
    ]
  },
  {
    "id": "page_134_line013",
    "text": "   Сформулируйте ответ на главный вопрос параграфа и  обоснуй-",
    "bbox": [
      0,
      260,
      500,
      275
    ]
  },
  {
    "id": "page_134_line014",
    "text": "те его 2—3 аргументами.?",
    "bbox": [
      0,
      280,
      500,
      295
    ]
  },
  {
    "id": "page_134_line015",
    "text": "ДОПОЛНИТЕЛЬНЫЕ МАТЕРИАЛЫ ",
    "bbox": [
      0,
      300,
      500,
      315
    ]
  },
  {
    "id": "page_134_line016",
    "text": "«МЁРТВЫЙ СЕЗОН» .  Худ. фильм 1968 г., реж. С. Кулиш.",
    "bbox": [
      0,
      320,
      500,
      335
    ]
  }
]