[
  {
    "id": "page_201_line000",
    "text": "200 ГЛАВА I",
    "bbox": [
      0,
      0,
      500,
      15
    ]
  },
  {
    "id": "page_201_line001",
    "text": " Вопросы и задания",
    "bbox": [
      0,
      20,
      500,
      35
    ]
  },
  {
    "id": "page_201_line002",
    "text": "1. Сформулируйте причины (не менее трёх), сделавшие возможным наступле-",
    "bbox": [
      0,
      40,
      500,
      55
    ]
  },
  {
    "id": "page_201_line003",
    "text": "ние разрядки. Какие цели преследовали СССР и США, идя по пути разрядки?",
    "bbox": [
      0,
      60,
      500,
      75
    ]
  },
  {
    "id": "page_201_line004",
    "text": "2. Какое из двух изображений, приведённых в  начале параграфа, в  большей мере может служить иллюстрацией понятия «разрядка международной на-",
    "bbox": [
      0,
      80,
      500,
      95
    ]
  },
  {
    "id": "page_201_line005",
    "text": "пряжённости»?",
    "bbox": [
      0,
      100,
      500,
      115
    ]
  },
  {
    "id": "page_201_line006",
    "text": "3. Какие из положений Заключительного акта Совещания по безопасности ",
    "bbox": [
      0,
      120,
      500,
      135
    ]
  },
  {
    "id": "page_201_line007",
    "text": "и  сотрудничеству в Европе страны Запада пытались использовать в ходе  ",
    "bbox": [
      0,
      140,
      500,
      155
    ]
  },
  {
    "id": "page_201_line008",
    "text": "идеологического противостояния с СССР?",
    "bbox": [
      0,
      160,
      500,
      175
    ]
  },
  {
    "id": "page_201_line009",
    "text": "4. Вам поручено подготовить развёрнутый ответ по теме «Отношения СССР ",
    "bbox": [
      0,
      180,
      500,
      195
    ]
  },
  {
    "id": "page_201_line010",
    "text": "с  социалистическими странами в  1960-х  — начале 1980-х гг.». Составьте сложный план, в соответствии с которым вы будете освещать эту тему. План ",
    "bbox": [
      0,
      200,
      500,
      215
    ]
  },
  {
    "id": "page_201_line011",
    "text": "должен содержать не менее трёх пунктов, непосредственно раскрывающих ",
    "bbox": [
      0,
      220,
      500,
      235
    ]
  },
  {
    "id": "page_201_line012",
    "text": "тему, из которых два или более детализированы в подпунктах.",
    "bbox": [
      0,
      240,
      500,
      255
    ]
  },
  {
    "id": "page_201_line013",
    "text": "5. С помощью дополнительных источников информации выясните, какую по -",
    "bbox": [
      0,
      260,
      500,
      275
    ]
  },
  {
    "id": "page_201_line014",
    "text": "мощь оказывал СССР развивающимся странам в 1964—1985 гг. Как данная помощь сказалась на развитии этих государств?",
    "bbox": [
      0,
      280,
      500,
      295
    ]
  },
  {
    "id": "page_201_line015",
    "text": "6. На карте покажите очаги международной напряжённости в  1964—1985  гг. Интересы каких стран сталкивались в данных регионах? Предположите, по -",
    "bbox": [
      0,
      300,
      500,
      315
    ]
  },
  {
    "id": "page_201_line016",
    "text": "чему именно эти регионы были точками международной напряжённости.",
    "bbox": [
      0,
      320,
      500,
      335
    ]
  },
  {
    "id": "page_201_line017",
    "text": "7*.  В исторической науке существуют дискуссионные проблемы, по которым высказываются различные, часто противоречивые точки зрения. Ниже при-",
    "bbox": [
      0,
      340,
      500,
      355
    ]
  },
  {
    "id": "page_201_line018",
    "text": "ведена одна из спорных точек зрения, существующих в исторической науке.",
    "bbox": [
      0,
      360,
      500,
      375
    ]
  },
  {
    "id": "page_201_line019",
    "text": "  Внешнеполитический курс советского руководства в  1960—1970-х  гг. был основан на принципах мирного сотрудничества со странами Запада.",
    "bbox": [
      0,
      380,
      500,
      395
    ]
  },
  {
    "id": "page_201_line020",
    "text": "  Используя исторические знания, приведите два аргумента, которыми мож-",
    "bbox": [
      0,
      400,
      500,
      415
    ]
  },
  {
    "id": "page_201_line021",
    "text": "но  подтвердить данную точку зрения, и  два аргумента, которыми можно  ",
    "bbox": [
      0,
      420,
      500,
      435
    ]
  },
  {
    "id": "page_201_line022",
    "text": "опровергнуть её.",
    "bbox": [
      0,
      440,
      500,
      455
    ]
  },
  {
    "id": "page_201_line023",
    "text": "Работаем с ХРОНОЛОГИЕЙ ",
    "bbox": [
      0,
      460,
      500,
      475
    ]
  },
  {
    "id": "page_201_line024",
    "text": "Расположите в  хронологической последовательности исторические собы-тия. Запишите в тетради цифры, которыми обозначены исторические собы-тия, в правильной последовательности.",
    "bbox": [
      0,
      480,
      500,
      495
    ]
  },
  {
    "id": "page_201_line025",
    "text": "1) подписание Заключительного акта Совещания по безопасности и сотруд-",
    "bbox": [
      0,
      500,
      500,
      515
    ]
  },
  {
    "id": "page_201_line026",
    "text": "ничеству в Европе",
    "bbox": [
      0,
      520,
      500,
      535
    ]
  },
  {
    "id": "page_201_line027",
    "text": "2) окончание войны США во Вьетнаме",
    "bbox": [
      0,
      540,
      500,
      555
    ]
  },
  {
    "id": "page_201_line028",
    "text": "3) ввод советских войск в Афганистан4) ввод войск Варшавского договора в Чехословакию",
    "bbox": [
      0,
      560,
      500,
      575
    ]
  },
  {
    "id": "page_201_line029",
    "text": "5) война между Аргентиной и Великобританией за Фолклендские (Мальвин-",
    "bbox": [
      0,
      580,
      500,
      595
    ]
  },
  {
    "id": "page_201_line030",
    "text": "ские) острова",
    "bbox": [
      0,
      600,
      500,
      615
    ]
  },
  {
    "id": "page_201_line031",
    "text": "Работаем с ПОНЯТИЯМИ ",
    "bbox": [
      0,
      620,
      500,
      635
    ]
  },
  {
    "id": "page_201_line032",
    "text": "Раскройте смысл понятия «разрядка международной напряжённости». При-",
    "bbox": [
      0,
      640,
      500,
      655
    ]
  },
  {
    "id": "page_201_line033",
    "text": "ведите один исторический факт, конкретизирующий данное понятие.",
    "bbox": [
      0,
      660,
      500,
      675
    ]
  }
]