[
  {
    "id": "page_153_line000",
    "text": "152 ГЛАВА I",
    "bbox": [
      0,
      0,
      500,
      15
    ]
  },
  {
    "id": "page_153_line001",
    "text": "2) начало косыгинской реформы в промышленности",
    "bbox": [
      0,
      20,
      500,
      35
    ]
  },
  {
    "id": "page_153_line002",
    "text": "3) начало VIII пятилетки",
    "bbox": [
      0,
      40,
      500,
      55
    ]
  },
  {
    "id": "page_153_line003",
    "text": "4) начало реформ Дэн Сяопина в Китае",
    "bbox": [
      0,
      60,
      500,
      75
    ]
  },
  {
    "id": "page_153_line004",
    "text": "Работаем с ПОНЯТИЯМИ ",
    "bbox": [
      0,
      80,
      500,
      95
    ]
  },
  {
    "id": "page_153_line005",
    "text": "Раскройте смысл понятия «хозрасчёт». Приведите один исторический  ",
    "bbox": [
      0,
      100,
      500,
      115
    ]
  },
  {
    "id": "page_153_line006",
    "text": "факт, конкретизирующий данное понятие.",
    "bbox": [
      0,
      120,
      500,
      135
    ]
  },
  {
    "id": "page_153_line007",
    "text": "Работаем с ИСТОЧНИКОМ ",
    "bbox": [
      0,
      140,
      500,
      155
    ]
  },
  {
    "id": "page_153_line008",
    "text": "Прочитайте фрагмент постановления «О строительстве Байкало-Амурской ",
    "bbox": [
      0,
      160,
      500,
      175
    ]
  },
  {
    "id": "page_153_line009",
    "text": "железнодорожной магистрали» (8 июля 1974 г.). Ответьте на вопросы и вы-полните задания.",
    "bbox": [
      0,
      180,
      500,
      195
    ]
  },
  {
    "id": "page_153_line010",
    "text": "«В целях дальнейшего развития производительных сил Восточной  ",
    "bbox": [
      0,
      200,
      500,
      215
    ]
  },
  {
    "id": "page_153_line011",
    "text": "Сибири и Дальнего Востока... Центральный Комитет КПСС и Совет  ",
    "bbox": [
      0,
      220,
      500,
      235
    ]
  },
  {
    "id": "page_153_line012",
    "text": "Министров СССР",
    "bbox": [
      0,
      240,
      500,
      255
    ]
  },
  {
    "id": "page_153_line013",
    "text": "постановляют…",
    "bbox": [
      0,
      260,
      500,
      275
    ]
  },
  {
    "id": "page_153_line014",
    "text": "а) построить в 1974—1983 годах Байкало-Амурскую железнодорожную ",
    "bbox": [
      0,
      280,
      500,
      295
    ]
  },
  {
    "id": "page_153_line015",
    "text": "магистраль протяжённостью 3145 км от г. Усть-Кута (ст. Лена) до г. Ком-сомольска-на-Амуре через Нижнеангарск, Чару, Тынду, Ургал…",
    "bbox": [
      0,
      300,
      500,
      315
    ]
  },
  {
    "id": "page_153_line016",
    "text": "в) сдать в постоянную эксплуатацию Байкало-Амурскую железно-",
    "bbox": [
      0,
      320,
      500,
      335
    ]
  },
  {
    "id": "page_153_line017",
    "text": "дорожную магистраль в 1983 году…",
    "bbox": [
      0,
      340,
      500,
      355
    ]
  },
  {
    "id": "page_153_line018",
    "text": "2. Установить на 1975—1980 годы объём капитальных вложений на ",
    "bbox": [
      0,
      360,
      500,
      375
    ]
  },
  {
    "id": "page_153_line019",
    "text": "строительство Байкало-Амурской железнодорожной магистрали в разме-ре 3570 млн рублей…",
    "bbox": [
      0,
      380,
      500,
      395
    ]
  },
  {
    "id": "page_153_line020",
    "text": "10. Государственному комитету Совета Министров СССР по профес-",
    "bbox": [
      0,
      400,
      500,
      415
    ]
  },
  {
    "id": "page_153_line021",
    "text": "сионально-техническому образованию и Совету Министров РСФСР предусмотреть в планах на 1975—1978 годы подготовку для Министерства транспортного строительства 13 тыс. квалифицированных рабочих для строительства Байкало-Амурской железнодорожной магистрали, в том числе в 1975 году 2 тыс. человек, в 1976 году 3 тыс. человек, в 1977 году 4 тыс. человек и в 1978 году 4 тыс. человек…",
    "bbox": [
      0,
      420,
      500,
      435
    ]
  },
  {
    "id": "page_153_line022",
    "text": "23. Одобрить инициативу ЦК ВЛКСМ, объявившего строительство ",
    "bbox": [
      0,
      440,
      500,
      455
    ]
  },
  {
    "id": "page_153_line023",
    "text": "Байкало-Амурской железнодорожной магистрали Всесоюзной ударной комсомольской стройкой, о направлении на эту стройку по комсомоль-ским путёвкам квалифицированных рабочих с промышленных предпри-ятий и строек страны с тем, чтобы начиная с 1975 года на строительстве Байкало-Амурской железнодорожной магистрали ежегодно работало не менее 20 тыс. человек молодёжи.",
    "bbox": [
      0,
      460,
      500,
      475
    ]
  },
  {
    "id": "page_153_line024",
    "text": "ЦК компартий союзных республик, крайкомам и обкомам КПСС ",
    "bbox": [
      0,
      480,
      500,
      495
    ]
  },
  {
    "id": "page_153_line025",
    "text": "оказывать помощь комсомольским организациям в работе по направ-лению молодёжи на строительство Байкало-Амурской железнодорожной магистрали».",
    "bbox": [
      0,
      500,
      500,
      515
    ]
  }
]