[
  {
    "id": "page_256_line000",
    "text": "255 § 23. Национальная политика и подъём национальных движений. Распад СССР",
    "bbox": [
      0,
      0,
      500,
      15
    ]
  },
  {
    "id": "page_256_line001",
    "text": "3 Противостояние между союзным Центром и партийным руко -",
    "bbox": [
      0,
      20,
      500,
      35
    ]
  },
  {
    "id": "page_256_line002",
    "text": "водством республик. Чем больше союзная власть делала уступок, ",
    "bbox": [
      0,
      40,
      500,
      55
    ]
  },
  {
    "id": "page_256_line003",
    "text": "тем более радикальными становились требования республик по ",
    "bbox": [
      0,
      60,
      500,
      75
    ]
  },
  {
    "id": "page_256_line004",
    "text": "расширению их прав и изменению форм советской федерации, вплоть до выхода из состава СССР.",
    "bbox": [
      0,
      80,
      500,
      95
    ]
  },
  {
    "id": "page_256_line005",
    "text": "Весной 1990 г. началось провозглашение союзными республи-",
    "bbox": [
      0,
      100,
      500,
      115
    ]
  },
  {
    "id": "page_256_line006",
    "text": "ками своего «суверенного статуса» в составе СССР или объявление независимости. Первыми это сделали Литва, Эстония и Латвия.  ",
    "bbox": [
      0,
      120,
      500,
      135
    ]
  },
  {
    "id": "page_256_line007",
    "text": "Начался процесс, который получил название «парад суверените-тов», а фактически — развала СССР.",
    "bbox": [
      0,
      140,
      500,
      155
    ]
  },
  {
    "id": "page_256_line008",
    "text": "За считаные месяцы высшие органы власти союзных и боль-",
    "bbox": [
      0,
      160,
      500,
      175
    ]
  },
  {
    "id": "page_256_line009",
    "text": "шинства автономных республик приняли декларации о суверени-тете и верховенстве республиканских законов над союзными. Рес-публики объявлялись собственниками «своих» ресурсов, земли и другого имущества, которые в соответствии с Конституцией СССР принадлежали всему народу страны. В части республик были при-",
    "bbox": [
      0,
      180,
      500,
      195
    ]
  },
  {
    "id": "page_256_line010",
    "text": "няты законы о государственном языке (языке титульной нации), даже заявлено о создании собственных армий, своей валюты.",
    "bbox": [
      0,
      200,
      500,
      215
    ]
  },
  {
    "id": "page_256_line011",
    "text": "Результатом «парада суверенитетов» стало заметное перерас-",
    "bbox": [
      0,
      220,
      500,
      235
    ]
  },
  {
    "id": "page_256_line012",
    "text": "пределение политической власти от центральных (союзных) орга-нов власти к республиканским.",
    "bbox": [
      0,
      240,
      500,
      255
    ]
  },
  {
    "id": "page_256_line013",
    "text": "Эти события привели к «войне законов» — республиканские ",
    "bbox": [
      0,
      260,
      500,
      275
    ]
  },
  {
    "id": "page_256_line014",
    "text": "власти нередко отказывались признавать законы, принятые  ",
    "bbox": [
      0,
      280,
      500,
      295
    ]
  },
  {
    "id": "page_256_line015",
    "text": "Верховным Советом СССР, Указы Президента СССР фактически не исполнялись.",
    "bbox": [
      0,
      300,
      500,
      315
    ]
  },
  {
    "id": "page_256_line016",
    "text": "Этот процесс шёл в нарушение и Конституции СССР, и Кон-",
    "bbox": [
      0,
      320,
      500,
      335
    ]
  },
  {
    "id": "page_256_line017",
    "text": "ституций союзных республик. Декларация, принятая в  Литве,  ",
    "bbox": [
      0,
      340,
      500,
      355
    ]
  },
  {
    "id": "page_256_line018",
    "text": "вообще заявляла о прекращении действия Конституции СССР на «своей» территории и «восстановлении» Литовской республики, существовавшей до Второй мировой войны.",
    "bbox": [
      0,
      360,
      500,
      375
    ]
  },
  {
    "id": "page_256_line019",
    "text": "В марте 1990 г. III Съезд народных депутатов СССР объявил не-",
    "bbox": [
      0,
      380,
      500,
      395
    ]
  },
  {
    "id": "page_256_line020",
    "text": "действительным одностороннее провозглашение независимости Литвой до установления законного порядка выхода из СССР. 3 апре-ля 1990 г. был принят закон «О порядке решения вопросов, связан-ных с выходом союзной республики из СССР». Он предусматривал проведение референдума, а также установление переходного перио-да, в течение которого должна была быть определена принадлеж-ность общесоюзной собственности и урегулированы финансово-  ",
    "bbox": [
      0,
      400,
      500,
      415
    ]
  },
  {
    "id": "page_256_line021",
    "text": "кредитные и имущественные отношения с  другими республиками.",
    "bbox": [
      0,
      420,
      500,
      435
    ]
  }
]