[
  {
    "id": "page_183_line000",
    "text": "182 ГЛАВА I",
    "bbox": [
      0,
      0,
      500,
      15
    ]
  },
  {
    "id": "page_183_line001",
    "text": " ПОДВЕДЁМ ИТОГИ",
    "bbox": [
      0,
      20,
      500,
      35
    ]
  },
  {
    "id": "page_183_line002",
    "text": "Жизнь людей в городе и на селе менялась к лучшему. Неуклон-",
    "bbox": [
      0,
      40,
      500,
      55
    ]
  },
  {
    "id": "page_183_line003",
    "text": "но росли доходы граждан, менялась структура питания, улуч шались ",
    "bbox": [
      0,
      60,
      500,
      75
    ]
  },
  {
    "id": "page_183_line004",
    "text": "жилищные условия. Однако общественные ожидания опережали ",
    "bbox": [
      0,
      80,
      500,
      95
    ]
  },
  {
    "id": "page_183_line005",
    "text": "реальный рост жизненного уровня. В этих условиях официальная пропаганда порождала скептицизм и недоверие людей. Это осо-бенно сильно проявилось в кругах интеллигенции.",
    "bbox": [
      0,
      100,
      500,
      115
    ]
  },
  {
    "id": "page_183_line006",
    "text": " Вопросы и задания",
    "bbox": [
      0,
      120,
      500,
      135
    ]
  },
  {
    "id": "page_183_line007",
    "text": "1. С опорой на конкретные исторические факты проиллюстрируйте общее  ",
    "bbox": [
      0,
      140,
      500,
      155
    ]
  },
  {
    "id": "page_183_line008",
    "text": "повышение жизненного уровня советских граждан в 1964—1985 гг. Какими ",
    "bbox": [
      0,
      160,
      500,
      175
    ]
  },
  {
    "id": "page_183_line009",
    "text": "факторами был обусловлен данный процесс?",
    "bbox": [
      0,
      180,
      500,
      195
    ]
  },
  {
    "id": "page_183_line010",
    "text": "2. Что такое товары длительного пользования? Приведите примеры выравни-вания обеспеченности городского и  сельского населения товарами этой  ",
    "bbox": [
      0,
      200,
      500,
      215
    ]
  },
  {
    "id": "page_183_line011",
    "text": "категории.",
    "bbox": [
      0,
      220,
      500,
      235
    ]
  },
  {
    "id": "page_183_line012",
    "text": "3. Как связаны между собой понятия «дефицит» и «теневой рынок»?",
    "bbox": [
      0,
      240,
      500,
      255
    ]
  },
  {
    "id": "page_183_line013",
    "text": "4. Докажите, что в  1964—1985  гг. правительство уделяло большое внимание решению жилищной проблемы.",
    "bbox": [
      0,
      260,
      500,
      275
    ]
  },
  {
    "id": "page_183_line014",
    "text": "5. Какова была цель раздачи садово-огородных участков? ",
    "bbox": [
      0,
      280,
      500,
      295
    ]
  },
  {
    "id": "page_183_line015",
    "text": "6. Что такое «магнитофонная революция»? Как это повлияло на формирова-",
    "bbox": [
      0,
      300,
      500,
      315
    ]
  },
  {
    "id": "page_183_line016",
    "text": "ние общественных настроений?",
    "bbox": [
      0,
      320,
      500,
      335
    ]
  },
  {
    "id": "page_183_line017",
    "text": "Работаем с ПОНЯТИЯМИ ",
    "bbox": [
      0,
      340,
      500,
      355
    ]
  },
  {
    "id": "page_183_line018",
    "text": "Раскройте смысл понятия «клуб самодеятельной песни».",
    "bbox": [
      0,
      360,
      500,
      375
    ]
  },
  {
    "id": "page_183_line019",
    "text": "Работаем с ИСТОЧНИКОМ ",
    "bbox": [
      0,
      380,
      500,
      395
    ]
  },
  {
    "id": "page_183_line020",
    "text": "Прочитайте Моральный кодекс строителя коммунизма — свод принципов коммунистической морали, вошедших в Программу КПСС, принятую  ",
    "bbox": [
      0,
      400,
      500,
      415
    ]
  },
  {
    "id": "page_183_line021",
    "text": "XXII съездом партии. Ответьте на вопросы и выполните задания.",
    "bbox": [
      0,
      420,
      500,
      435
    ]
  },
  {
    "id": "page_183_line022",
    "text": "«Моральный кодекс строителя коммунизма включает такие нрав-",
    "bbox": [
      0,
      440,
      500,
      455
    ]
  },
  {
    "id": "page_183_line023",
    "text": "ственные принципы:",
    "bbox": [
      0,
      460,
      500,
      475
    ]
  },
  {
    "id": "page_183_line024",
    "text": "— преданность делу коммунизма, любовь к социалистической Роди-",
    "bbox": [
      0,
      480,
      500,
      495
    ]
  },
  {
    "id": "page_183_line025",
    "text": "не, к странам социализма;",
    "bbox": [
      0,
      500,
      500,
      515
    ]
  },
  {
    "id": "page_183_line026",
    "text": "— добросовестный труд на благо общества: кто не работает, тот не ест;",
    "bbox": [
      0,
      520,
      500,
      535
    ]
  },
  {
    "id": "page_183_line027",
    "text": "— забота каждого о сохранении и умножении общественного достояния;",
    "bbox": [
      0,
      540,
      500,
      555
    ]
  },
  {
    "id": "page_183_line028",
    "text": "— высокое сознание общественного долга, нетерпимость к нарушени-",
    "bbox": [
      0,
      560,
      500,
      575
    ]
  },
  {
    "id": "page_183_line029",
    "text": "ям общественных интересов;",
    "bbox": [
      0,
      580,
      500,
      595
    ]
  }
]